[
    { "pre": [
            {
                "id": 0,
                "product": "Lorem",
                "price": 100
            },
            {
                "id": 1,
                "product": "Lorem",
                "price": 100
            },
            {
                "id": 2,
                "product": "Lorem",
                "price": 100
            }
        ],

      "main": [
            {
                "id": 3,
                "product": "Lorem",
                "price": 100
            },
            {
                "id": 4,
                "product": "Lorem",
                "price": 100
            },
            {
                "id": 5,
                "product": "Lorem",
                "price": 100
            },
            {
                "id": 6,
                "product": "Lorem",
                "price": 100
            },
            {
                "id": 7,
                "product": "Lorem",
                "price": 100
            },
            {
                "id": 8,
                "product": "Lorem",
                "price": 100
            }
        ],

     "desert": [
            {
                "id": 9,
                "product": "Lorem",
                "price": 100
            },
            {
                "id": 10,
                "product": "Lorem",
                "price": 100
            },
            {
                "id": 11,
                "product": "Lorem",
                "price": 100
            }
        ]
    }
]
